llm_sambanova.py
llm_sambanova-0.1.dist-info/LICENSE
llm_sambanova-0.1.dist-info/METADATA
llm_sambanova-0.1.dist-info/WHEEL
llm_sambanova-0.1.dist-info/entry_points.txt
llm_sambanova-0.1.dist-info/top_level.txt
llm_sambanova-0.1.dist-info/RECORD
