Metadata-Version: 2.1
Name: llm-sambanova
Version: 0.1
Summary: LLM plugin for models hosted by SambaNova
Author: Nick Mystic
License: MIT
Project-URL: Homepage, https://github.com/ghostofpokemon/llm-sambanova
Project-URL: Changelog, https://github.com/ghostofpokemon/llm-sambanova/releases
Project-URL: Issues, https://github.com/ghostofpokemon/llm-sambanova/issues
Project-URL: CI, https://github.com/ghostofpokemon/llm-sambanova/actions
Classifier: License :: OSI Approved :: Apache Software License
License-File: LICENSE
Requires-Dist: llm >=0.8
Requires-Dist: httpx
Provides-Extra: test
Requires-Dist: pytest ; extra == 'test'
Requires-Dist: pytest-httpx ; extra == 'test'
